real_environment/__init__.py
real_environment/real_environment.py
real_environment-1.0.dist-info/DESCRIPTION.rst
real_environment-1.0.dist-info/METADATA
real_environment-1.0.dist-info/RECORD
real_environment-1.0.dist-info/WHEEL
real_environment-1.0.dist-info/metadata.json
real_environment-1.0.dist-info/top_level.txt
